IndicoWp/__init__.py
IndicoWp/config.py
IndicoWp/controller.py
IndicoWp/database.py
IndicoWp/install.py
IndicoWp/main.py
IndicoWp/proto.py
IndicoWp/reference.py
IndicoWp/wordpress.py
IndicoWp/indico/__init__.py
IndicoWp/indico/controller.py
IndicoWp/indico/event.py
IndicoWp/indico/indico.py
IndicoWp/indico/observe.py
IndicoWp/indico/persistency.py
IndicoWp/tests/test_config.py
IndicoWp/tests/test_event.py
IndicoWp/tests/test_indico.py
IndicoWp/views/__init__.py
IndicoWp/views/text.py
IndicoWp/views/wordpress.py
indico_wp-0.1.0.13.data/data/post.html
indico_wp-0.1.0.13.dist-info/DESCRIPTION.rst
indico_wp-0.1.0.13.dist-info/METADATA
indico_wp-0.1.0.13.dist-info/RECORD
indico_wp-0.1.0.13.dist-info/WHEEL
indico_wp-0.1.0.13.dist-info/metadata.json
indico_wp-0.1.0.13.dist-info/top_level.txt
