Metadata-Version: 2.0
Name: indico-wp
Version: 0.1.0.13
Summary: A tool for a wordpress server which will automatically post science events from indico website
Home-page: https://github.com/the16thpythonist/IndicoWp
Author: Jonas Teufel
Author-email: jonseb1998@gmail.com
License: MIT
Platform: UNKNOWN
Requires-Python: >=3, <4
Requires-Dist: SQLAlchemy (>=1.2)
Requires-Dist: jinja2 (>=2.2)
Requires-Dist: mysqlclient (>=1.2)
Requires-Dist: python-wordpress-xmlrpc (>=2.3)
Requires-Dist: requests (>=2.0)
Requires-Dist: tabulate (>=0.8)
